stop_idle_sessions/__init__.py
stop_idle_sessions/exception.py
stop_idle_sessions/getent.py
stop_idle_sessions/list_set.py
stop_idle_sessions/logind.py
stop_idle_sessions/main.py
stop_idle_sessions/ps.py
stop_idle_sessions/ss.py
stop_idle_sessions/tty.py
stop_idle_sessions/widget.py
stop_idle_sessions/x11.py
stop_idle_sessions-0.9.4.dist-info/LICENSE
stop_idle_sessions-0.9.4.dist-info/METADATA
stop_idle_sessions-0.9.4.dist-info/WHEEL
stop_idle_sessions-0.9.4.dist-info/top_level.txt
stop_idle_sessions-0.9.4.dist-info/RECORD
