Metadata-Version: 2.2
Name: stop-idle-sessions
Version: 0.9.4
Summary: Stop idle `systemd-logind` sessions to prevent interactive access from unattended terminals. E.g., a laptop left unlocked in a coffee shop, with an SSH session into an internal network resource.
Home-page: https://github.com/liverwust/stop-idle-sessions
Author: Louis Wust
Author-email: louiswust@fastmail.fm
License: MIT License
Classifier: Development Status :: 4 - Beta
Classifier: Environment :: No Input/Output (Daemon)
Classifier: Intended Audience :: System Administrators
Classifier: License :: OSI Approved :: MIT License
Classifier: Operating System :: POSIX :: Linux
Classifier: Programming Language :: Python :: 3
Classifier: Programming Language :: Python :: 3.6
Classifier: Programming Language :: Python :: 3.9
Classifier: Topic :: Security
Classifier: Topic :: System :: Shells
Classifier: Topic :: System :: System Shells
Classifier: Topic :: System :: Systems Administration
Classifier: Topic :: Terminals
Classifier: Topic :: Utilities
Requires-Python: >= 3.6
License-File: LICENSE
Requires-Dist: PyGObject>=3.28.3
Requires-Dist: psutil>=5.4.3
Requires-Dist: python-xlib>=0.33
Dynamic: author
Dynamic: author-email
Dynamic: classifier
Dynamic: description
Dynamic: description-content-type
Dynamic: home-page
Dynamic: license
Dynamic: requires-dist
Dynamic: requires-python
Dynamic: summary
